{"paths":{},"types":[],"uuids":["18o433XG5C6ZK9l6GZ9NAH","20Y5RP/wVALJj7yIW7EAfl","43UxelkhJHWIlUE6+SM1kA","45/Gi4Ru5I7646Xb91ifAh","7bo3x/EBFI9YlZndfBSSOb","02delMVqdBD70a/HSD99FK","17InxzD0JDHoFm2O7nsehV","2c7cf+nVhEmKOiy+KvcCrq","47J/igKXxEC4eASDxi6Kp9","a2MjXRFdtLlYQ5ouAFv/+R","ecpdLyjvZBwrvm+cedCcQy"],"scenes":{"db://assets/scene/game.fire":1},"redirect":[5,0,10,0],"deps":["internal"],"packs":{"0179a422e":[6,1,7,8,4,9],"0d6da8bf3":[0,2,3]},"name":"main","importBase":"import","nativeBase":"native","debug":false,"isZip":false,"encrypted":false,"versions":{"import":["0179a422e","090d0","0d6da8bf3","c36e8"],"native":[0,"16f02",2,"4252e",3,"b3d9f",4,"cfdd6"]}}